MANIFEST.in
requirements.txt
setup.cfg
setup.py
test-requirements.txt
rabbitracer/__init__.py
rabbitracer.egg-info/PKG-INFO
rabbitracer.egg-info/SOURCES.txt
rabbitracer.egg-info/dependency_links.txt
rabbitracer.egg-info/entry_points.txt
rabbitracer.egg-info/not-zip-safe
rabbitracer.egg-info/requires.txt
rabbitracer.egg-info/top_level.txt