Metadata-Version: 1.1
Name: rabbitracer
Version: 0.1.2
Summary: RabbitMQ Firehose Dump Script
Home-page: https://github.com/momijiame/rabbitracer
Author: momijiame
Author-email: amedama.ginmokusei@gmail.com
License: UNKNOWN
Platform: UNKNOWN
Classifier: Programming Language :: Python :: 2
Classifier: Programming Language :: Python :: 2.7
Classifier: Development Status :: 4 - Beta
Classifier: License :: OSI Approved :: Apache Software License
Classifier: Intended Audience :: Developers
Classifier: Natural Language :: Japanese
Classifier: Operating System :: POSIX
